tap_s3_csv_philly/__init__.py
tap_s3_csv_philly/schemas/wireless_products.json
tap_s3_csv_philly-0.1.0.dist-info/LICENSE
tap_s3_csv_philly-0.1.0.dist-info/METADATA
tap_s3_csv_philly-0.1.0.dist-info/WHEEL
tap_s3_csv_philly-0.1.0.dist-info/entry_points.txt
tap_s3_csv_philly-0.1.0.dist-info/top_level.txt
tap_s3_csv_philly-0.1.0.dist-info/RECORD
