Metadata-Version: 2.1
Name: tap-s3-csv-philly
Version: 0.1.0
Summary: Singer.io tap for extracting data
Home-page: http://singer.io
Author: Stitch
Author-email: UNKNOWN
License: UNKNOWN
Platform: UNKNOWN
Classifier: Programming Language :: Python :: 3 :: Only
Requires-Dist: singer-python (>=5.0.12)
Requires-Dist: requests (==2.20.0)
Requires-Dist: boto3
Requires-Dist: botocore
